zgrandom/__init__.py
zgrandom/setup.py
zgrandom-0.2.dist-info/METADATA
zgrandom-0.2.dist-info/WHEEL
zgrandom-0.2.dist-info/top_level.txt
zgrandom-0.2.dist-info/RECORD
