Metadata-Version: 2.1
Name: zgrandom
Version: 0.2
Summary: Alternative Of Random Module
Author: Zaz Yagmi
